mcp_code_analyzer/__init__.py
mcp_code_analyzer/__main__.py
mcp_code_analyzer/config.py
mcp_code_analyzer/server/__init__.py
mcp_code_analyzer/server/handlers.py
mcp_code_analyzer/tools/__init__.py
mcp_code_analyzer/tools/analysis_tools.py
mcp_code_analyzer/tools/base.py
mcp_code_analyzer/tools/dependency_tools.py
mcp_code_analyzer/tools/file_tools.py
mcp_code_analyzer/tools/logger.py
mcp_code_analyzer/tools/manager.py
mcp_code_analyzer/tools/modification_tools.py
mcp_code_analyzer/tools/pattern_tools.py
mcp_code_analyzer/tools/project_tools.py
mcp_code_analyzer/tools/reference_tools.py
mcp_code_analyzer/tools/search_tools.py
mcp_code_analyzer/tools/version_manager.py
mseep_mcp_code_analyzer-0.1.4.dist-info/METADATA
mseep_mcp_code_analyzer-0.1.4.dist-info/WHEEL
mseep_mcp_code_analyzer-0.1.4.dist-info/entry_points.txt
mseep_mcp_code_analyzer-0.1.4.dist-info/licenses/LICENCE
mseep_mcp_code_analyzer-0.1.4.dist-info/RECORD
